MMCpip
