Metadata-Version: 2.1
Name: MMCpip
Version: 0.1.1
Summary: 一个让中文开发者更方便pip的库
Home-page: https://github.com/mmc2009/MMCpip.git
Author: MMC(毛毛虫)
Author-email: outlook_5EDC1733BB36CC27@outlook.com
License: MIT
Platform: UNKNOWN
Classifier: License :: OSI Approved :: MIT License
Classifier: Programming Language :: Python
Classifier: Programming Language :: Python :: 3
Classifier: Programming Language :: Python :: 3.6
Classifier: Programming Language :: Python :: Implementation :: CPython
Classifier: Programming Language :: Python :: Implementation :: PyPy
Requires-Python: >=3.6.0
